EZProjects/__init__.py
EZProjects/library.py
EZProjects-0.0.2.dist-info/LICENSE
EZProjects-0.0.2.dist-info/METADATA
EZProjects-0.0.2.dist-info/WHEEL
EZProjects-0.0.2.dist-info/top_level.txt
EZProjects-0.0.2.dist-info/RECORD
