Metadata-Version: 2.1
Name: EZProjects
Version: 0.0.2
Summary: A package that is made for AI Examination for students in grade 9 and CBSE.
Home-page: UNKNOWN
Author: MuhammadShafeeq (Muhammad Shafeeq)
Author-email: <muhammadshafeeq1595@gmail.com>
License: UNKNOWN
Keywords: python,string,formatting,slicing
Platform: UNKNOWN
Classifier: Development Status :: 1 - Planning
Classifier: Intended Audience :: Developers
Classifier: Programming Language :: Python :: 3
Classifier: Operating System :: Unix
Classifier: Operating System :: MacOS :: MacOS X
Classifier: Operating System :: Microsoft :: Windows
